{
  "tools": {
    "axe": {
      "name": "Axe",
      "icon": "minecraft:diamond_axe",
      "toollist": [
        "AWWayofTime:boundAxe",
        "ActuallyAdditions:diamondPaxel",
        "ActuallyAdditions:emeraldPaxel",
        "ActuallyAdditions:goldPaxel",
        "ActuallyAdditions:ironPaxel",
        "ActuallyAdditions:itemAxeCrystalBlack",
        "ActuallyAdditions:itemAxeCrystalBlue",
        "ActuallyAdditions:itemAxeCrystalGreen",
        "ActuallyAdditions:itemAxeCrystalLightBlue",
        "ActuallyAdditions:itemAxeCrystalRed",
        "ActuallyAdditions:itemAxeCrystalWhite",
        "ActuallyAdditions:itemAxeEmerald",
        "ActuallyAdditions:itemAxeObsidian",
        "ActuallyAdditions:itemAxeQuartz",
        "ActuallyAdditions:itemPaxelCrystalBlack",
        "ActuallyAdditions:itemPaxelCrystalBlue",
        "ActuallyAdditions:itemPaxelCrystalGreen",
        "ActuallyAdditions:itemPaxelCrystalLightBlue",
        "ActuallyAdditions:itemPaxelCrystalRed",
        "ActuallyAdditions:itemPaxelCrystalWhite",
        "ActuallyAdditions:obsidianPaxel",
        "ActuallyAdditions:paxelMTBronze",
        "ActuallyAdditions:paxelMTGlowstone",
        "ActuallyAdditions:paxelMTLapisLazuli",
        "ActuallyAdditions:paxelMTObsidian",
        "ActuallyAdditions:paxelMTOsmium",
        "ActuallyAdditions:paxelMTSteel",
        "ActuallyAdditions:paxelTFBronze",
        "ActuallyAdditions:paxelTFCopper",
        "ActuallyAdditions:paxelTFElectrum",
        "ActuallyAdditions:paxelTFInvar",
        "ActuallyAdditions:paxelTFLead",
        "ActuallyAdditions:paxelTFNickel",
        "ActuallyAdditions:paxelTFPlatinum",
        "ActuallyAdditions:paxelTFSilver",
        "ActuallyAdditions:paxelTFTin",
        "ActuallyAdditions:quartzPaxel",
        "ActuallyAdditions:stonePaxel",
        "ActuallyAdditions:woodenPaxel",
        "Avaritia:Infinity_Axe",
        "BiomesOPlenty:axeAmethyst",
        "BiomesOPlenty:axeMud",
        "Botania:elementiumAxe",
        "Botania:manasteelAxe",
        "Botania:terraAxe",
        "Calculator:ElectricAxe",
        "Calculator:EndForgedAxe",
        "Calculator:EnrichedGoldAxe",
        "Calculator:FireDiamondAxe",
        "Calculator:FlawlessDiamondAxe",
        "Calculator:RedstonedAxe",
        "Calculator:ReinforcedAxe",
        "Calculator:ReinforcedIronAxe",
        "Calculator:WeakenedDiamondAxe",
        "EnderIO:item.darkSteel_axe",
        "ExtraPlanets:blueDiamondAxe",
        "ExtraPlanets:blueGemAxe",
        "ExtraPlanets:carbonAxe",
        "ExtraPlanets:crystalAxe",
        "ExtraPlanets:greenDiamondAxe",
        "ExtraPlanets:magnesiumAxe",
        "ExtraPlanets:mercuryAxe",
        "ExtraPlanets:palladiumAxe",
        "ExtraPlanets:purpleDiamondAxe",
        "ExtraPlanets:redDiamondAxe",
        "ExtraPlanets:redGemAxe",
        "ExtraPlanets:tungstenAxe",
        "ExtraPlanets:uraniumAxe",
        "ExtraPlanets:whiteGemAxe",
        "ExtraPlanets:yellowDiamondAxe",
        "ExtraPlanets:zincAxe",
        "ExtraUtilities:defoliageAxe",
        "GalacticraftCore:item.steel_axe",
        "GalacticraftMars:item.deshAxe",
        "GalacticraftMars:item.titanium_axe",
        "MekanismTools:BronzeAxe",
        "MekanismTools:BronzePaxel",
        "MekanismTools:DiamondPaxel",
        "MekanismTools:GlowstoneAxe",
        "MekanismTools:GlowstonePaxel",
        "MekanismTools:GoldPaxel",
        "MekanismTools:IronPaxel",
        "MekanismTools:LapisLazuliAxe",
        "MekanismTools:LapisLazuliPaxel",
        "MekanismTools:ObsidianAxe",
        "MekanismTools:ObsidianPaxel",
        "MekanismTools:OsmiumAxe",
        "MekanismTools:OsmiumPaxel",
        "MekanismTools:SteelAxe",
        "MekanismTools:SteelPaxel",
        "MekanismTools:StonePaxel",
        "MekanismTools:WoodPaxel",
        "Natura:natura.axe.bloodwood",
        "Natura:natura.axe.darkwood",
        "Natura:natura.axe.fusewood",
        "Natura:natura.axe.ghostwood",
        "Natura:natura.axe.netherquartz",
        "RedstoneArsenal:tool.axeFlux",
        "TConstruct:hatchet",
        "Thaumcraft:ItemAxeElemental",
        "Thaumcraft:ItemAxeThaumium",
        "Thaumcraft:ItemAxeVoid",
        "ThermalFoundation:tool.axeBronze",
        "ThermalFoundation:tool.axeCopper",
        "ThermalFoundation:tool.axeElectrum",
        "ThermalFoundation:tool.axeInvar",
        "ThermalFoundation:tool.axeLead",
        "ThermalFoundation:tool.axeNickel",
        "ThermalFoundation:tool.axePlatinum",
        "ThermalFoundation:tool.axeSilver",
        "ThermalFoundation:tool.axeTin",
        "TwilightForest:item.ironwoodAxe",
        "TwilightForest:item.knightlyAxe",
        "TwilightForest:item.minotaurAxe",
        "TwilightForest:item.steeleafAxe",
        "Ztones:splatAxe",
        "appliedenergistics2:item.ToolCertusQuartzAxe",
        "appliedenergistics2:item.ToolNetherQuartzAxe",
        "magicalcrops:magicalcrops_AccioAxe",
        "magicalcrops:magicalcrops_CrucioAxe",
        "magicalcrops:magicalcrops_ImperioAxe",
        "magicalcrops:magicalcrops_ZivicioAxe",
        "minecraft:diamond_axe",
        "minecraft:golden_axe",
        "minecraft:iron_axe",
        "minecraft:stone_axe",
        "minecraft:wooden_axe"
      ],
      "blocklist": [
        "BiomesOPlenty:appleLeaves",
        "BiomesOPlenty:colorizedLeaves1",
        "BiomesOPlenty:colorizedLeaves2",
        "BiomesOPlenty:leaves1",
        "BiomesOPlenty:leaves2",
        "BiomesOPlenty:leaves3",
        "BiomesOPlenty:leaves4",
        "BiomesOPlenty:logs1",
        "BiomesOPlenty:logs2",
        "BiomesOPlenty:logs3",
        "BiomesOPlenty:logs4",
        "BiomesOPlenty:persimmonLeaves",
        "Calculator:AmethystLog/0",
        "Calculator:DiamondLog/0",
        "Calculator:PearLog/0",
        "Calculator:TanzaniteLog/0",
        "Natura:Dark Leaves",
        "Natura:Dark Tree/0",
        "Natura:Dark Tree/1",
        "Natura:Rare Leaves",
        "Natura:Rare Tree/0",
        "Natura:Rare Tree/1",
        "Natura:Rare Tree/2",
        "Natura:Rare Tree/3",
        "Natura:floraleaves",
        "Natura:floraleavesnocolor",
        "Natura:redwood/1",
        "Natura:tree/0",
        "Natura:tree/1",
        "Natura:tree/2",
        "Natura:tree/3",
        "Natura:willow/0",
        "Thaumcraft:blockMagicalLog/0",
        "Thaumcraft:blockMagicalLog/1",
        "TwilightForest:tile.TFLeaves",
        "TwilightForest:tile.TFLog",
        "TwilightForest:tile.TFMagicLeaves",
        "TwilightForest:tile.TFMagicLog",
        "harvestcraft:pamCinnamon/0",
        "harvestcraft:pamMaple/0",
        "harvestcraft:pamPaperbark/0",
        "minecraft:fence",
        "minecraft:leaves",
        "minecraft:leaves2",
        "minecraft:log",
        "minecraft:log2",
        "witchery:witchleaves",
        "witchery:witchlog"
      ]
    },
    "hoe": {
      "name": "Hoe",
      "icon": "minecraft:diamond_hoe",
      "toollist": [
        "ActuallyAdditions:diamondPaxel",
        "ActuallyAdditions:emeraldPaxel",
        "ActuallyAdditions:goldPaxel",
        "ActuallyAdditions:ironPaxel",
        "ActuallyAdditions:itemHoeCrystalBlack",
        "ActuallyAdditions:itemHoeCrystalBlue",
        "ActuallyAdditions:itemHoeCrystalGreen",
        "ActuallyAdditions:itemHoeCrystalLightBlue",
        "ActuallyAdditions:itemHoeCrystalRed",
        "ActuallyAdditions:itemHoeCrystalWhite",
        "ActuallyAdditions:itemHoeEmerald",
        "ActuallyAdditions:itemHoeObsidian",
        "ActuallyAdditions:itemHoeQuartz",
        "ActuallyAdditions:itemPaxelCrystalBlack",
        "ActuallyAdditions:itemPaxelCrystalBlue",
        "ActuallyAdditions:itemPaxelCrystalGreen",
        "ActuallyAdditions:itemPaxelCrystalLightBlue",
        "ActuallyAdditions:itemPaxelCrystalRed",
        "ActuallyAdditions:itemPaxelCrystalWhite",
        "ActuallyAdditions:obsidianPaxel",
        "ActuallyAdditions:paxelMTBronze",
        "ActuallyAdditions:paxelMTGlowstone",
        "ActuallyAdditions:paxelMTLapisLazuli",
        "ActuallyAdditions:paxelMTObsidian",
        "ActuallyAdditions:paxelMTOsmium",
        "ActuallyAdditions:paxelMTSteel",
        "ActuallyAdditions:paxelTFBronze",
        "ActuallyAdditions:paxelTFCopper",
        "ActuallyAdditions:paxelTFElectrum",
        "ActuallyAdditions:paxelTFInvar",
        "ActuallyAdditions:paxelTFLead",
        "ActuallyAdditions:paxelTFNickel",
        "ActuallyAdditions:paxelTFPlatinum",
        "ActuallyAdditions:paxelTFSilver",
        "ActuallyAdditions:paxelTFTin",
        "ActuallyAdditions:quartzPaxel",
        "ActuallyAdditions:stonePaxel",
        "ActuallyAdditions:woodenPaxel",
        "BiomesOPlenty:hoeAmethyst",
        "BiomesOPlenty:hoeMud",
        "Calculator:ElectricHoe",
        "Calculator:EndForgedHoe",
        "Calculator:EnrichedGoldHoe",
        "Calculator:FireDiamondHoe",
        "Calculator:FlawlessDiamondHoe",
        "Calculator:RedstoneHoe",
        "Calculator:ReinforcedHoe",
        "Calculator:ReinforcedIronHoe",
        "Calculator:WeakenedDiamondHoe",
        "DraconicEvolution:draconicHoe",
        "ExtraPlanets:blueDiamondHoe",
        "ExtraPlanets:blueGemHoe",
        "ExtraPlanets:carbonHoe",
        "ExtraPlanets:crystalHoe",
        "ExtraPlanets:greenDiamondHoe",
        "ExtraPlanets:magnesiumHoe",
        "ExtraPlanets:mercuryHoe",
        "ExtraPlanets:palladiumHoe",
        "ExtraPlanets:purpleDiamondHoe",
        "ExtraPlanets:redDiamondHoe",
        "ExtraPlanets:redGemHoe",
        "ExtraPlanets:tungstenHoe",
        "ExtraPlanets:uraniumHoe",
        "ExtraPlanets:whiteGemHoe",
        "ExtraPlanets:yellowDiamondHoe",
        "ExtraPlanets:zincHoe",
        "ExtraUtilities:temporalHoe",
        "GalacticraftCore:item.steel_hoe",
        "GalacticraftMars:item.deshHoe",
        "GalacticraftMars:item.titanium_hoe",
        "TConstruct:mattock",
        "Thaumcraft:ItemHoeElemental",
        "Thaumcraft:ItemHoeThaumium",
        "Thaumcraft:ItemHoeVoid",
        "ThermalFoundation:tool.hoeBronze",
        "ThermalFoundation:tool.hoeCopper",
        "ThermalFoundation:tool.hoeElectrum",
        "ThermalFoundation:tool.hoeInvar",
        "ThermalFoundation:tool.hoeLead",
        "ThermalFoundation:tool.hoeNickel",
        "ThermalFoundation:tool.hoePlatinum",
        "ThermalFoundation:tool.hoeSilver",
        "ThermalFoundation:tool.hoeTin",
        "TwilightForest:item.ironwoodHoe",
        "TwilightForest:item.steeleafHoe",
        "appliedenergistics2:item.ToolCertusQuartzHoe",
        "appliedenergistics2:item.ToolNetherQuartzHoe",
        "magicalcrops:magicalcrops_AccioHoe",
        "magicalcrops:magicalcrops_CrucioHoe",
        "magicalcrops:magicalcrops_ImperioHoe",
        "magicalcrops:magicalcrops_ZivicioHoe",
        "minecraft:diamond_hoe",
        "minecraft:golden_hoe",
        "minecraft:iron_hoe",
        "minecraft:stone_hoe",
        "minecraft:wooden_hoe"
      ],
      "blocklist": [
        "minecraft:carrots",
        "minecraft:melon_block",
        "minecraft:potatoes",
        "minecraft:pumpkin",
        "minecraft:wheat"
      ]
    },
    "pickaxe": {
      "name": "Pickaxe",
      "icon": "minecraft:diamond_pickaxe",
      "toollist": [
        "AWWayofTime:boundPickaxe",
        "ActuallyAdditions:diamondPaxel",
        "ActuallyAdditions:emeraldPaxel",
        "ActuallyAdditions:goldPaxel",
        "ActuallyAdditions:ironPaxel",
        "ActuallyAdditions:itemPaxelCrystalBlack",
        "ActuallyAdditions:itemPaxelCrystalBlue",
        "ActuallyAdditions:itemPaxelCrystalGreen",
        "ActuallyAdditions:itemPaxelCrystalLightBlue",
        "ActuallyAdditions:itemPaxelCrystalRed",
        "ActuallyAdditions:itemPaxelCrystalWhite",
        "ActuallyAdditions:itemPickaxeCrystalBlack",
        "ActuallyAdditions:itemPickaxeCrystalBlue",
        "ActuallyAdditions:itemPickaxeCrystalGreen",
        "ActuallyAdditions:itemPickaxeCrystalLightBlue",
        "ActuallyAdditions:itemPickaxeCrystalRed",
        "ActuallyAdditions:itemPickaxeCrystalWhite",
        "ActuallyAdditions:itemPickaxeEmerald",
        "ActuallyAdditions:itemPickaxeObsidian",
        "ActuallyAdditions:itemPickaxeQuartz",
        "ActuallyAdditions:obsidianPaxel",
        "ActuallyAdditions:paxelMTBronze",
        "ActuallyAdditions:paxelMTGlowstone",
        "ActuallyAdditions:paxelMTLapisLazuli",
        "ActuallyAdditions:paxelMTObsidian",
        "ActuallyAdditions:paxelMTOsmium",
        "ActuallyAdditions:paxelMTSteel",
        "ActuallyAdditions:paxelTFBronze",
        "ActuallyAdditions:paxelTFCopper",
        "ActuallyAdditions:paxelTFElectrum",
        "ActuallyAdditions:paxelTFInvar",
        "ActuallyAdditions:paxelTFLead",
        "ActuallyAdditions:paxelTFNickel",
        "ActuallyAdditions:paxelTFPlatinum",
        "ActuallyAdditions:paxelTFSilver",
        "ActuallyAdditions:paxelTFTin",
        "ActuallyAdditions:quartzPaxel",
        "ActuallyAdditions:stonePaxel",
        "ActuallyAdditions:woodenPaxel",
        "Avaritia:Infinity_Pickaxe",
        "BiomesOPlenty:pickaxeAmethyst",
        "BiomesOPlenty:pickaxeMud",
        "Botania:elementiumPick",
        "Botania:glassPick",
        "Botania:manasteelPick",
        "Calculator:ElectricPickaxe",
        "Calculator:EndForgedPickaxe",
        "Calculator:EnrichedGoldPickaxe",
        "Calculator:FireDiamondPickaxe",
        "Calculator:FlawlessDiamondPickaxe",
        "Calculator:RedstonePickaxe",
        "Calculator:ReinforcedIronPickaxe",
        "Calculator:ReinforcedPickaxe",
        "Calculator:WeakenedDiamondPickaxe",
        "EnderIO:item.darkSteel_pickaxe",
        "ExtraPlanets:blueDiamondPickaxe",
        "ExtraPlanets:blueGemPickaxe",
        "ExtraPlanets:carbonPickaxe",
        "ExtraPlanets:crystalPickaxe",
        "ExtraPlanets:greenDiamondPickaxe",
        "ExtraPlanets:magnesiumPickaxe",
        "ExtraPlanets:mercuryPickaxe",
        "ExtraPlanets:palladiumPickaxe",
        "ExtraPlanets:purpleDiamondPickaxe",
        "ExtraPlanets:redDiamondPickaxe",
        "ExtraPlanets:redGemPickaxe",
        "ExtraPlanets:tungstenPickaxe",
        "ExtraPlanets:uraniumPickaxe",
        "ExtraPlanets:whiteGemPickaxe",
        "ExtraPlanets:yellowDiamondPickaxe",
        "ExtraPlanets:zincPickaxe",
        "ExtraUtilities:destructionpickaxe",
        "GalacticraftCore:item.steel_pickaxe",
        "GalacticraftMars:item.deshPick",
        "GalacticraftMars:item.deshPickSlime",
        "GalacticraftMars:item.titanium_pickaxe",
        "MekanismTools:BronzePaxel",
        "MekanismTools:BronzePickaxe",
        "MekanismTools:DiamondPaxel",
        "MekanismTools:GlowstonePaxel",
        "MekanismTools:GlowstonePickaxe",
        "MekanismTools:GoldPaxel",
        "MekanismTools:IronPaxel",
        "MekanismTools:LapisLazuliPaxel",
        "MekanismTools:LapisLazuliPickaxe",
        "MekanismTools:ObsidianPaxel",
        "MekanismTools:ObsidianPickaxe",
        "MekanismTools:OsmiumPaxel",
        "MekanismTools:OsmiumPickaxe",
        "MekanismTools:SteelPaxel",
        "MekanismTools:SteelPickaxe",
        "MekanismTools:StonePaxel",
        "MekanismTools:WoodPaxel",
        "Natura:natura.pickaxe.bloodwood",
        "Natura:natura.pickaxe.darkwood",
        "Natura:natura.pickaxe.fusewood",
        "Natura:natura.pickaxe.ghostwood",
        "Natura:natura.pickaxe.netherquartz",
        "ProjectE:item.pe_dm_pick",
        "ProjectE:item.pe_rm_pick",
        "RedstoneArsenal:tool.pickaxeFlux",
        "TConstruct:pickaxe",
        "Thaumcraft:ItemPickThaumium",
        "Thaumcraft:ItemPickVoid",
        "Thaumcraft:ItemPickaxeElemental",
        "ThermalFoundation:tool.pickaxeBronze",
        "ThermalFoundation:tool.pickaxeCopper",
        "ThermalFoundation:tool.pickaxeElectrum",
        "ThermalFoundation:tool.pickaxeInvar",
        "ThermalFoundation:tool.pickaxeLead",
        "ThermalFoundation:tool.pickaxeNickel",
        "ThermalFoundation:tool.pickaxePlatinum",
        "ThermalFoundation:tool.pickaxeSilver",
        "ThermalFoundation:tool.pickaxeTin",
        "appliedenergistics2:item.ToolCertusQuartzPickaxe",
        "appliedenergistics2:item.ToolNetherQuartzPickaxe",
        "magicalcrops:magicalcrops_AccioPickaxe",
        "magicalcrops:magicalcrops_CrucioPickaxe",
        "magicalcrops:magicalcrops_ImperioPickaxe",
        "magicalcrops:magicalcrops_ZivicioPickaxe",
        "minecraft:diamond_pickaxe",
        "minecraft:golden_pickaxe",
        "minecraft:iron_pickaxe",
        "minecraft:stone_pickaxe",
        "minecraft:wooden_pickaxe",
        "witchery:kobolditepickaxe"
      ],
      "blocklist": [
        "ActuallyAdditions:blockMisc/3",
        "BigReactors:YelloriteOre/0",
        "BiomesOPlenty:gemOre/2",
        "BiomesOPlenty:gemOre/4",
        "BiomesOPlenty:gemOre/6",
        "BiomesOPlenty:gemOre/8",
        "BiomesOPlenty:gemOre/10",
        "BiomesOPlenty:gemOre/12",
        "BiomesOPlenty:gemOre/14",
        "DraconicEvolution:draconiumOre/0",
        "ExtraPlanets:iapetus/3",
        "ExtraPlanets:iapetus/4",
        "ExtraPlanets:iapetus/5",
        "ExtraPlanets:oberon/3",
        "ExtraPlanets:oberon/4",
        "ExtraPlanets:oberon/5",
        "ExtraPlanets:tile.callisto/3",
        "ExtraPlanets:tile.callisto/4",
        "ExtraPlanets:tile.callisto/5",
        "ExtraPlanets:tile.ceres/3",
        "ExtraPlanets:tile.ceres/4",
        "ExtraPlanets:tile.ceres/5",
        "ExtraPlanets:tile.ceres/6",
        "ExtraPlanets:tile.deimos/3",
        "ExtraPlanets:tile.deimos/4",
        "ExtraPlanets:tile.deimos/5",
        "ExtraPlanets:tile.deimos/6",
        "ExtraPlanets:tile.eris/3",
        "ExtraPlanets:tile.eris/4",
        "ExtraPlanets:tile.eris/5",
        "ExtraPlanets:tile.eris/7",
        "ExtraPlanets:tile.europa/3",
        "ExtraPlanets:tile.europa/4",
        "ExtraPlanets:tile.europa/5",
        "ExtraPlanets:tile.ganymede/3",
        "ExtraPlanets:tile.ganymede/4",
        "ExtraPlanets:tile.ganymede/5",
        "ExtraPlanets:tile.io/3",
        "ExtraPlanets:tile.io/4",
        "ExtraPlanets:tile.io/5",
        "ExtraPlanets:tile.jupiter/3",
        "ExtraPlanets:tile.jupiter/4",
        "ExtraPlanets:tile.jupiter/5",
        "ExtraPlanets:tile.jupiter/6",
        "ExtraPlanets:tile.jupiter/7",
        "ExtraPlanets:tile.jupiter/10",
        "ExtraPlanets:tile.kepler22b/2",
        "ExtraPlanets:tile.kepler22b/3",
        "ExtraPlanets:tile.kepler22b/4",
        "ExtraPlanets:tile.kepler22b/5",
        "ExtraPlanets:tile.kepler22b/6",
        "ExtraPlanets:tile.kepler22b/7",
        "ExtraPlanets:tile.kepler22b/8",
        "ExtraPlanets:tile.kepler22b/9",
        "ExtraPlanets:tile.kepler22b/10",
        "ExtraPlanets:tile.kepler22b/13",
        "ExtraPlanets:tile.mercury/3",
        "ExtraPlanets:tile.mercury/4",
        "ExtraPlanets:tile.mercury/5",
        "ExtraPlanets:tile.mercury/6",
        "ExtraPlanets:tile.neptune/3",
        "ExtraPlanets:tile.neptune/4",
        "ExtraPlanets:tile.neptune/5",
        "ExtraPlanets:tile.neptune/6",
        "ExtraPlanets:tile.neptune/9",
        "ExtraPlanets:tile.phobos/3",
        "ExtraPlanets:tile.phobos/4",
        "ExtraPlanets:tile.phobos/5",
        "ExtraPlanets:tile.phobos/6",
        "ExtraPlanets:tile.pluto/3",
        "ExtraPlanets:tile.pluto/4",
        "ExtraPlanets:tile.pluto/5",
        "ExtraPlanets:tile.pluto/6",
        "ExtraPlanets:tile.rhea/3",
        "ExtraPlanets:tile.rhea/4",
        "ExtraPlanets:tile.rhea/5",
        "ExtraPlanets:tile.saturn/3",
        "ExtraPlanets:tile.saturn/4",
        "ExtraPlanets:tile.saturn/5",
        "ExtraPlanets:tile.saturn/6",
        "ExtraPlanets:tile.saturn/11",
        "ExtraPlanets:tile.titan/3",
        "ExtraPlanets:tile.titan/4",
        "ExtraPlanets:tile.titan/5",
        "ExtraPlanets:tile.triton/3",
        "ExtraPlanets:tile.triton/4",
        "ExtraPlanets:tile.triton/5",
        "ExtraPlanets:tile.uranus/3",
        "ExtraPlanets:tile.uranus/6",
        "ExtraPlanets:tile.venus/3",
        "ExtraPlanets:tile.venus/4",
        "ExtraPlanets:tile.venus/5",
        "ExtraPlanets:tile.venus/6",
        "ExtraPlanets:titania/3",
        "ExtraPlanets:titania/4",
        "ExtraPlanets:titania/5",
        "GalacticraftCore:tile.gcBlockCore/5",
        "GalacticraftCore:tile.gcBlockCore/6",
        "GalacticraftCore:tile.gcBlockCore/7",
        "GalacticraftCore:tile.gcBlockCore/8",
        "GalacticraftCore:tile.moonBlock/0",
        "GalacticraftCore:tile.moonBlock/1",
        "GalacticraftCore:tile.moonBlock/2",
        "GalacticraftMars:tile.asteroidsBlock/3",
        "GalacticraftMars:tile.asteroidsBlock/4",
        "GalacticraftMars:tile.asteroidsBlock/5",
        "GalacticraftMars:tile.mars/0",
        "GalacticraftMars:tile.mars/1",
        "GalacticraftMars:tile.mars/2",
        "GalacticraftMars:tile.mars/3",
        "ImmersiveEngineering:ore/0",
        "ImmersiveEngineering:ore/1",
        "ImmersiveEngineering:ore/2",
        "ImmersiveEngineering:ore/3",
        "ImmersiveEngineering:ore/4",
        "Mekanism:OreBlock/0",
        "Mekanism:OreBlock/1",
        "Mekanism:OreBlock/2",
        "NetherOres:tile.netherores.ore.0/0",
        "NetherOres:tile.netherores.ore.0/1",
        "NetherOres:tile.netherores.ore.0/2",
        "NetherOres:tile.netherores.ore.0/3",
        "NetherOres:tile.netherores.ore.0/4",
        "NetherOres:tile.netherores.ore.0/5",
        "NetherOres:tile.netherores.ore.0/6",
        "NetherOres:tile.netherores.ore.0/7",
        "NetherOres:tile.netherores.ore.0/8",
        "NetherOres:tile.netherores.ore.0/9",
        "NetherOres:tile.netherores.ore.0/10",
        "NetherOres:tile.netherores.ore.0/11",
        "NetherOres:tile.netherores.ore.0/12",
        "NetherOres:tile.netherores.ore.0/13",
        "NetherOres:tile.netherores.ore.0/14",
        "NetherOres:tile.netherores.ore.0/15",
        "NetherOres:tile.netherores.ore.1/0",
        "NetherOres:tile.netherores.ore.1/1",
        "NetherOres:tile.netherores.ore.1/2",
        "NetherOres:tile.netherores.ore.1/3",
        "NetherOres:tile.netherores.ore.1/4",
        "NetherOres:tile.netherores.ore.1/5",
        "NetherOres:tile.netherores.ore.1/6",
        "NetherOres:tile.netherores.ore.1/7",
        "NetherOres:tile.netherores.ore.1/8",
        "NetherOres:tile.netherores.ore.1/9",
        "NetherOres:tile.netherores.ore.1/10",
        "NetherOres:tile.netherores.ore.1/11",
        "NetherOres:tile.netherores.ore.1/12",
        "NetherOres:tile.netherores.ore.1/13",
        "NetherOres:tile.netherores.ore.1/14",
        "NetherOres:tile.netherores.ore.1/15",
        "TConstruct:SearedBrick/1",
        "TConstruct:SearedBrick/2",
        "TConstruct:SearedBrick/3",
        "TConstruct:SearedBrick/4",
        "TConstruct:SearedBrick/5",
        "TConstruct:ore.berries.one/0",
        "TConstruct:ore.berries.one/1",
        "TConstruct:ore.berries.one/2",
        "TConstruct:ore.berries.one/3",
        "TConstruct:ore.berries.two/0",
        "TConstruct:ore.berries.two/1",
        "Thaumcraft:blockCustomOre/0",
        "Thaumcraft:blockCustomOre/1",
        "Thaumcraft:blockCustomOre/2",
        "Thaumcraft:blockCustomOre/3",
        "Thaumcraft:blockCustomOre/4",
        "Thaumcraft:blockCustomOre/5",
        "Thaumcraft:blockCustomOre/6",
        "Thaumcraft:blockCustomOre/7",
        "ThermalFoundation:Ore/0",
        "ThermalFoundation:Ore/1",
        "ThermalFoundation:Ore/2",
        "ThermalFoundation:Ore/3",
        "ThermalFoundation:Ore/4",
        "ThermalFoundation:Ore/5",
        "ThermalFoundation:Ore/6",
        "appliedenergistics2:tile.OreQuartz/0",
        "appliedenergistics2:tile.OreQuartzCharged/0",
        "harvestcraft:salt",
        "magicalcrops:magicalcrops_MinicioOre/0",
        "minecraft:coal_ore",
        "minecraft:cobblestone_wall",
        "minecraft:diamond_ore",
        "minecraft:emerald_ore",
        "minecraft:glowstone",
        "minecraft:gold_ore",
        "minecraft:iron_ore",
        "minecraft:lapis_ore",
        "minecraft:lit_redstone_ore",
        "minecraft:mossy_cobblestone",
        "minecraft:nether_brick_fence",
        "minecraft:obsidian",
        "minecraft:quartz_ore",
        "minecraft:redstone_ore"
      ]
    },
    "shears": {
      "name": "Shears",
      "icon": "minecraft:shears",
      "toollist": [
        "BiomesOPlenty:scytheAmethyst",
        "BiomesOPlenty:scytheDiamond",
        "BiomesOPlenty:scytheGold",
        "BiomesOPlenty:scytheIron",
        "BiomesOPlenty:scytheMud",
        "BiomesOPlenty:scytheStone",
        "BiomesOPlenty:scytheWood",
        "minecraft:shears"
      ],
      "blocklist": [
        "BiomesOPlenty:appleLeaves",
        "BiomesOPlenty:colorizedLeaves1",
        "BiomesOPlenty:colorizedLeaves2",
        "BiomesOPlenty:leaves1",
        "BiomesOPlenty:leaves2",
        "BiomesOPlenty:leaves3",
        "BiomesOPlenty:leaves4",
        "BiomesOPlenty:persimmonLeaves",
        "Natura:Dark Leaves",
        "Natura:Rare Leaves",
        "Natura:floraleaves",
        "Natura:floraleavesnocolor",
        "TwilightForest:tile.TFLeaves",
        "TwilightForest:tile.TFMagicLeaves",
        "minecraft:deadbush",
        "minecraft:leaves",
        "minecraft:leaves2",
        "minecraft:tallgrass",
        "minecraft:vine",
        "minecraft:web",
        "minecraft:wool",
        "witchery:witchleaves"
      ]
    },
    "shovel": {
      "name": "Shovel",
      "icon": "minecraft:diamond_shovel",
      "toollist": [
        "AWWayofTime:boundShovel",
        "ActuallyAdditions:diamondPaxel",
        "ActuallyAdditions:emeraldPaxel",
        "ActuallyAdditions:goldPaxel",
        "ActuallyAdditions:ironPaxel",
        "ActuallyAdditions:itemPaxelCrystalBlack",
        "ActuallyAdditions:itemPaxelCrystalBlue",
        "ActuallyAdditions:itemPaxelCrystalGreen",
        "ActuallyAdditions:itemPaxelCrystalLightBlue",
        "ActuallyAdditions:itemPaxelCrystalRed",
        "ActuallyAdditions:itemPaxelCrystalWhite",
        "ActuallyAdditions:itemShovelCrystalBlack",
        "ActuallyAdditions:itemShovelCrystalBlue",
        "ActuallyAdditions:itemShovelCrystalGreen",
        "ActuallyAdditions:itemShovelCrystalLightBlue",
        "ActuallyAdditions:itemShovelCrystalRed",
        "ActuallyAdditions:itemShovelCrystalWhite",
        "ActuallyAdditions:itemShovelEmerald",
        "ActuallyAdditions:itemShovelObsidian",
        "ActuallyAdditions:itemShovelQuartz",
        "ActuallyAdditions:obsidianPaxel",
        "ActuallyAdditions:paxelMTBronze",
        "ActuallyAdditions:paxelMTGlowstone",
        "ActuallyAdditions:paxelMTLapisLazuli",
        "ActuallyAdditions:paxelMTObsidian",
        "ActuallyAdditions:paxelMTOsmium",
        "ActuallyAdditions:paxelMTSteel",
        "ActuallyAdditions:paxelTFBronze",
        "ActuallyAdditions:paxelTFCopper",
        "ActuallyAdditions:paxelTFElectrum",
        "ActuallyAdditions:paxelTFInvar",
        "ActuallyAdditions:paxelTFLead",
        "ActuallyAdditions:paxelTFNickel",
        "ActuallyAdditions:paxelTFPlatinum",
        "ActuallyAdditions:paxelTFSilver",
        "ActuallyAdditions:paxelTFTin",
        "ActuallyAdditions:quartzPaxel",
        "ActuallyAdditions:stonePaxel",
        "ActuallyAdditions:woodenPaxel",
        "Avaritia:Infinity_Shovel",
        "BiomesOPlenty:shovelAmethyst",
        "BiomesOPlenty:shovelMud",
        "Botania:elementiumShovel",
        "Botania:manasteelShovel",
        "Calculator:ElectricShovel",
        "Calculator:EndForgedShovel",
        "Calculator:EnrichedGoldShovel",
        "Calculator:FireDiamondShovel",
        "Calculator:FlawlessDiamondShovel",
        "Calculator:RedstoneShovel",
        "Calculator:ReinforcedIronShovel",
        "Calculator:ReinforcedShovel",
        "Calculator:WeakenedDiamondShovel",
        "ExtraPlanets:blueDiamondShovel",
        "ExtraPlanets:blueGemShovel",
        "ExtraPlanets:carbonShovel",
        "ExtraPlanets:crystalShovel",
        "ExtraPlanets:greenDiamondShovel",
        "ExtraPlanets:magnesiumShovel",
        "ExtraPlanets:mercuryShovel",
        "ExtraPlanets:palladiumShovel",
        "ExtraPlanets:purpleDiamondShovel",
        "ExtraPlanets:redDiamondShovel",
        "ExtraPlanets:redGemShovel",
        "ExtraPlanets:tungstenShovel",
        "ExtraPlanets:uraniumShovel",
        "ExtraPlanets:whiteGemShovel",
        "ExtraPlanets:yellowDiamondShovel",
        "ExtraPlanets:zincShovel",
        "ExtraUtilities:erosionShovel",
        "GalacticraftCore:item.steel_shovel",
        "GalacticraftMars:item.titanium_shovel",
        "MekanismTools:BronzePaxel",
        "MekanismTools:BronzeShovel",
        "MekanismTools:DiamondPaxel",
        "MekanismTools:GlowstonePaxel",
        "MekanismTools:GlowstoneShovel",
        "MekanismTools:GoldPaxel",
        "MekanismTools:IronPaxel",
        "MekanismTools:LapisLazuliPaxel",
        "MekanismTools:LapisLazuliShovel",
        "MekanismTools:ObsidianPaxel",
        "MekanismTools:ObsidianShovel",
        "MekanismTools:OsmiumPaxel",
        "MekanismTools:OsmiumShovel",
        "MekanismTools:SteelPaxel",
        "MekanismTools:SteelShovel",
        "MekanismTools:StonePaxel",
        "MekanismTools:WoodPaxel",
        "Natura:natura.shovel.bloodwood",
        "Natura:natura.shovel.darkwood",
        "Natura:natura.shovel.fusewood",
        "Natura:natura.shovel.ghostwood",
        "Natura:natura.shovel.netherquartz",
        "RedstoneArsenal:tool.shovelFlux",
        "TConstruct:mattock",
        "TConstruct:shovel",
        "Thaumcraft:ItemShovelElemental",
        "Thaumcraft:ItemShovelThaumium",
        "Thaumcraft:ItemShovelVoid",
        "ThermalFoundation:tool.shovelBronze",
        "ThermalFoundation:tool.shovelCopper",
        "ThermalFoundation:tool.shovelElectrum",
        "ThermalFoundation:tool.shovelInvar",
        "ThermalFoundation:tool.shovelLead",
        "ThermalFoundation:tool.shovelNickel",
        "ThermalFoundation:tool.shovelPlatinum",
        "ThermalFoundation:tool.shovelSilver",
        "ThermalFoundation:tool.shovelTin",
        "TwilightForest:item.ironwoodShovel",
        "TwilightForest:item.steeleafShovel",
        "appliedenergistics2:item.ToolCertusQuartzSpade",
        "appliedenergistics2:item.ToolNetherQuartzSpade",
        "magicalcrops:magicalcrops_AccioShovel",
        "magicalcrops:magicalcrops_CrucioShovel",
        "magicalcrops:magicalcrops_ImperioShovel",
        "magicalcrops:magicalcrops_ZivicioShovel",
        "minecraft:diamond_shovel",
        "minecraft:golden_shovel",
        "minecraft:iron_shovel",
        "minecraft:stone_shovel",
        "minecraft:wooden_shovel"
      ],
      "blocklist": [
        "TConstruct:GravelOre/0",
        "TConstruct:GravelOre/1",
        "TConstruct:GravelOre/2",
        "TConstruct:GravelOre/3",
        "TConstruct:GravelOre/4",
        "TConstruct:GravelOre/5",
        "minecraft:clay",
        "minecraft:gravel"
      ]
    }
  }
}